MANIFEST.in
README.rst
setup.cfg
setup.py
versioneer.py
bridgedb/Bridges.py
bridgedb/Bucket.py
bridgedb/Main.py
bridgedb/Stability.py
bridgedb/Storage.py
bridgedb/__init__.py
bridgedb/_langs.py
bridgedb/_version.py
bridgedb/bridgerequest.py
bridgedb/bridges.py
bridgedb/captcha.py
bridgedb/configure.py
bridgedb/crypto.py
bridgedb/distribute.py
bridgedb/filters.py
bridgedb/geo.py
bridgedb/interfaces.py
bridgedb/persistent.py
bridgedb/proxy.py
bridgedb/qrcodes.py
bridgedb/runner.py
bridgedb/safelog.py
bridgedb/schedule.py
bridgedb/sitecustomize.py
bridgedb/strings.py
bridgedb/translations.py
bridgedb/txrecaptcha.py
bridgedb/util.py
bridgedb.egg-info/PKG-INFO
bridgedb.egg-info/SOURCES.txt
bridgedb.egg-info/dependency_links.txt
bridgedb.egg-info/not-zip-safe
bridgedb.egg-info/requires.txt
bridgedb.egg-info/top_level.txt
bridgedb/email/__init__.py
bridgedb/email/autoresponder.py
bridgedb/email/distributor.py
bridgedb/email/dkim.py
bridgedb/email/request.py
bridgedb/email/server.py
bridgedb/email/templates.py
bridgedb/https/__init__.py
bridgedb/https/distributor.py
bridgedb/https/request.py
bridgedb/https/server.py
bridgedb/parse/__init__.py
bridgedb/parse/addr.py
bridgedb/parse/descriptors.py
bridgedb/parse/fingerprint.py
bridgedb/parse/headers.py
bridgedb/parse/nickname.py
bridgedb/parse/options.py
bridgedb/parse/versions.py
scripts/bridgedb
scripts/get-tor-exits
test/test_Bucket.py
test/test_Main.py
test/test_Storage.py
test/test_Tests.py
test/test_bridgedb.py
test/test_bridgerequest.py
test/test_bridges.py
test/test_captcha.py
test/test_configure.py
test/test_crypto.py
test/test_distribute.py
test/test_email_autoresponder.py
test/test_email_distributor.py
test/test_email_dkim.py
test/test_email_request.py
test/test_email_server.py
test/test_email_templates.py
test/test_filters.py
test/test_geo.py
test/test_https.py
test/test_https_distributor.py
test/test_https_request.py
test/test_https_server.py
test/test_interfaces.py
test/test_parse_addr.py
test/test_parse_descriptors.py
test/test_parse_headers.py
test/test_parse_nickname.py
test/test_parse_options.py
test/test_parse_versions.py
test/test_persistent.py
test/test_persistentSaveAndLoad.py
