Metadata-Version: 1.1
Name: bridgedb
Version: 0.3.6
Summary: Backend systems for distribution of Tor bridge relays
Home-page: https://www.torproject.org
Author: Isis Agora Lovecruft
Author-email: isis@torproject.org 0xA3ADB67A2CDB8B35
License: UNKNOWN
Download-URL: https://gitweb.torproject.org/bridgedb.git
Platform: UNKNOWN
